Workbook

Sheet Customers
A1: Customer ID | B1: C_Name | C1: C_phone | D1: Vehi_Num | E1: Vehi_brand | F1: Vehi_name | G1: Address | H1: F_Visit_Date | I1: L_Service_Date | J1: Next_Service | K1: Note
A2: {=IF(LEN(B2:B10520), "CUST"&TEXT(ROW(B2:B10520)-1,"0000"), "")} -> CUST0001 | B2: HARSHADBHAI VAGHELA | C2: 9898284327 | D2: GJ27CN9504 | E2: HEROPESSIONPROBLACK | F2: HEROPESSIONPRO | G2: GATRAD GAM | H2: 25/03/2023 | I2: 45010 | J2: =IF(I2="","",EDATE(I2,3)) -> 45102
A3: CUST0002 | B3: JASHWANT PRAJAPATI | C3: 9824820017 | D3: GJ27BJ9478 | E3: HONDASHINEBLACK | F3: HONDASHINE | H3: 27/05/2020 | I3: 43978 | J3: =IF(I3="","",EDATE(I3,3)) -> 44070
A4: CUST0003 | B4: NARESHBHAI PATEL | C4: 9924748010 | D4: GJ27E4534 | E4: ACTIVA BLACK | F4: ACTIVA | H4: 21/11/2022 | I4: 44886 | J4: =IF(I4="","",EDATE(I4,3)) -> 44978
A5: CUST0004 | B5: YOGESH MAHESHBHAI GAJJAR | C5: 9601065325 | D5: GJ27Q1004 | E5: ACTIVA BLACK | F5: ACTIVA | G5: B-85 NIGAM SOCIETY | H5: 30/11/2019 | I5: 43799 | J5: =IF(I5="","",EDATE(I5,3)) -> 43890
A6: CUST0005 | B6: UPENDRABHAI PATEL | C6: 9974591740 | D6: GJ01SB0672 | E6: MAHINDRACENTURIOBLAC | F6: MAHINDRACENTURIO | G6: B-1/41 AALOK - 5, | H6: 29/11/2022 | I6: 44894 | J6: =IF(I6="","",EDATE(I6,3)) -> 44985
A7: CUST0006 | B7: DHAVALBHAI | C7: 9726937785 | D7: GJ27BR2787 | E7: HEROPESSIONPROBLACK | F7: HEROPESSIONPRO | G7: AVDH RE | H7: 29/11/2019 | I7: 43798 | J7: =IF(I7="","",EDATE(I7,3)) -> 43890
A8: CUST0007 | B8: PRAKASHBHAI THAKOR | C8: 9824540194 | D8: GJ27J7699 | E8: DREEM YUGA | F8: HONDA | H8: 21/05/2023 | I8: 45067 | J8: =IF(I8="","",EDATE(I8,3)) -> 45159
A9: CUST0008 | B9: KIRAN BHAI PATEL | C9: 9924691071 | D9: GJ02BL5262 | E9: DREEM YUGA | F9: HONDA | G9: B102 KENSHASH | H9: 29/11/2019 | I9: 43798 | J9: =IF(I9="","",EDATE(I9,3)) -> 43890
A10: CUST0009 | B10: ANKIT PATEL | C10: 9737548662 | D10: GJ01JN6237 | E10: ACTIVA BLACK | F10: ACTIVA | H10: 28/10/2023 | I10: 45227 | J10: =IF(I10="","",EDATE(I10,3)) -> 45319
A11: CUST0010 | B11: DHARMIK BHARATBHAI PATEL | C11: 7777981411 | D11: GJ27BK9776 | E11: ACTIVABLACK | F11: ACTIVA 4G | G11: N501, UTSAV CITY | H11: 14/04/2023 | I11: 45030 | J11: =IF(I11="","",EDATE(I11,3)) -> 45121
A12: CUST0011 | B12: KEVALBHAI KIRITBHAI PATEL | C12: 9979124383 | D12: GJ27BG3046 | E12: ACTIVA | F12: ACTIVA 3G | G12: A-2 402,SHASHVAT-3 | H12: 45937 | I12: 45848 | J12: =IF(I12="","",EDATE(I12,3)) -> 45940
A13: CUST0012 | B13: NIKUBHAI PATEL | C13: 9099036478 | D13: GJ7BG5464 | E13: ACTIVA | F13: ACTIVA 3G | H13: 43508 | I13: 43801 | J13: =IF(I13="","",EDATE(I13,3)) -> 43892
A14: CUST0013 | B14: KISHANBHAI PATEL | C14: 9725812836 | D14: GJ27AF3505 | E14: SPLENDOR PLUS | F14: SPLENDOR PLUS | G14: F 301 AVADH RES | H14: 22/03/2023 | I14: 45007 | J14: =IF(I14="","",EDATE(I14,3)) -> 45099
A15: CUST0014 | B15: VIJAYBHAI PATEL | C15: 8153914181 | D15: GJ27BG5156 | E15: SHINE | F15: CB SHINE | G15: A 2/104 AKSHARDHAM RES | H15: 22/07/2025 | I15: 45860 | J15: =IF(I15="","",EDATE(I15,3)) -> 45952
A16: CUST0015 | B16: JAYKUMAR SANTIBHAI PRAJAPATI | C16: 9909773168 | D16: GJ24AE3372 | E16: DREEM YUGA | F16: HONDA | G16: RATANPURA GAM | H16: 43477 | I16: 43800 | J16: =IF(I16="","",EDATE(I16,3)) -> 43891
A17: CUST0016 | B17: JAY MAKWANA | C17: 8487811424 | D17: GJ27CD2995 | E17: HONDASHINEBLACK | F17: HONDASHINE | G17: BAPUNAGAR | H17: 21/08/2022 | I17: 44794 | J17: =IF(I17="","",EDATE(I17,3)) -> 44886
A18: CUST0017 | B18: CHANDRESHBHAI PATEL | C18: 9722265074 | D18: GJ27F1767 | E18: SPLENDOR PLUS | F18: SPLENDOR PLUS | G18: 65 AKSHARDHAM SOC | H18: - - | I18: 46012 | J18: =IF(I18="","",EDATE(I18,3)) -> 46102
A19: CUST0018 | B19: BHAVESH BHAI B PATEL | C19: 8140204097 | D19: GJ27BJ7884 | E19: PASSION PRO | F19: PASSION PRO | G19: D7 SWAMINARAYAN PARK | H19: 23/08/2020 | I19: 44066 | J19: =IF(I19="","",EDATE(I19,3)) -> 44158
A20: CUST0019 | B20: JAIMINBHAI PATEL | C20: 8780099699 | D20: GJ38C6212 | E20: SUZUKIGIXXER | F20: SUZUKIGIXXER | G20: L 404,USHAV CITY | H20: 46268 | I20: 46090 | J20: =IF(I20="","",EDATE(I20,3)) -> 46182
A21: CUST0020 | B21: SAKATI B GOHIL | C21: 9924503311 | D21: GJ27CK9688 | E21: PASSION PRO | F21: PASSION PRO | G21: A/83,SWAPNA SHRUSHTI SOC | H21: 45788 | I21: 45966 | J21: =IF(I21="","",EDATE(I21,3)) -> 46058
A22: CUST0021 | B22: SHILESH BHAI PANCHAL | C22: 9723335148 | D22: GJ01NM7895 | E22: PASSION PRO | F22: PASSION PRO | G22: Z,202 DEVNANDANSUPREM | H22: 44441 | I22: 44236 | J22: =IF(I22="","",EDATE(I22,3)) -> 44325
A23: CUST0022 | B23: KARTIK BHAI PATEL | C23: 9712932383 | D23: GJ27AG1367 | E23: ACTIVA WHITE | F23: ACTIVA | G23: PART1,J-101 KRISH AVENU | H23: - - | I23: 46012 | J23: =IF(I23="","",EDATE(I23,3)) -> 46102
A24: CUST0023 | B24: ALKESHBHAI DESAI | C24: 9824324807 | D24: GJ27BK6713 | E24: ACTIVA | F24: ACTIVA 3G | G24: 17 SHIVSANTI TENAMENT | H24: 44965 | I24: 45140 | J24: =IF(I24="","",EDATE(I24,3)) -> 45232
A25: CUST0024 | B25: CHINTAN BHAI PATRL | C25: 9601500509 | D25: GJ02BC5057 | E25: HEROXTREMBACK | F25: XTREME | G25: F-301 ALOK PERADE 1 | H25: - - | I25: 46012 | J25: =IF(I25="","",EDATE(I25,3)) -> 46102
A26: CUST0025 | B26: RKTGERJKER | C26: 3336464646 | D26: GJ1FR2971 | E26: PASSION PRO | F26: PASSION PRO | G26: RENKGNREREJKL | H26: - - | I26: 46012 | J26: =IF(I26="","",EDATE(I26,3)) -> 46102
A27: CUST0026 | B27: PARKASHBHAI THAKOR | C27: 9824540194 | D27: GJ02S7699 | E27: SPLENDOR PLUS | F27: SPLENDOR PLUS | G27: A-101 OMKAR RE, | H27: 31/08/2023 | I27: 45169 | J27: =IF(I27="","",EDATE(I27,3)) -> 45260
A28: CUST0027 | B28: HITESHBHAI | C28: 9427803151 | D28: GJ27AS3151 | E28: HUNK | F28: HUNK HERO | G28: SARNM RE | H28: 45874 | I28: 45785 | J28: =IF(I28="","",EDATE(I28,3)) -> 45877
A29: CUST0028 | B29: HIREN DESHI | C29: 7016991625 | D29: GJ27J5558 | E29: SPLENDOR PLUS | F29: SPLENDOR PLUS | G29: 01,CHITRKUT SOC | H29: 18/06/2020 | I29: 44000 | J29: =IF(I29="","",EDATE(I29,3)) -> 44092
A30: CUST0029 | B30: DHASHARATBHAI | C30: 9825913978 | D30: GJO1FB3346 | E30: SPLENDOR PLUS | F30: SPLENDOR PLUS | G30: 46 SHIVALAY SOC, | H30: - - | I30: 46012 | J30: =IF(I30="","",EDATE(I30,3)) -> 46102
A31: CUST0030 | B31: MUKESH BHAI GUPTA | C31: 8141866900 | D31: GJ27AK8333 | E31: BLACK | F31: TVSAPACHE160 | G31: H-201 SHREE SAREN FLAT | H31: 45575 | I31: 45575 | J31: =IF(I31="","",EDATE(I31,3)) -> 45667
A32: CUST0031 | B32: ANILBHAI DAVE | C32: 7383268947 | D32: GJ27BH6547 | E32: JUPITER BKACK | F32: JUPITER | G32: S-702 SUREYAM ELIGRANC | H32: 26/12/2025 | I32: 46017 | J32: =IF(I32="","",EDATE(I32,3)) -> 46107
A33: CUST0032 | B33: RAKESHBHAI SONI | C33: 9913545226 | D33: GJ01JL8209 | E33: PASSIN PLUS | F33: PASSIN PLUS | G33: M-303 MADHAV HOMES | H33: 43567 | I33: 43803 | J33: =IF(I33="","",EDATE(I33,3)) -> 43894
A34: CUST0033 | B34: CHIRAGBHAI PATEL. | C34: 9558555412 | D34: GJ01LV1773 | E34: AVENGER 150 | F34: AVENGER 150 STREET | G34: 23,KARNAVATI RO HAHUS | H34: 26/11/2021 | I34: 44526 | J34: =IF(I34="","",EDATE(I34,3)) -> 44618
A35: CUST0034 | B35: DIPAK BHAI MEVADA | C35: 8140461426 | D35: GJ084125 | E35: ACCESS125 OLD | F35: ACCESS125 | G35: G 406 SASHVAT MHADEV PART 2 | H35: 43567 | I35: 43803 | J35: =IF(I35="","",EDATE(I35,3)) -> 43894
A36: CUST0035 | B36: DIPAKBHAI MEVADA | C36: 8140461426 | D36: GJ08AF4125 | E36: ACCESS125 OLD | F36: ACCESS125 | G36: G-406,SASHVAT MHADEV PART-2 | H36: 28/02/2024 | I36: 45350 | J36: =IF(I36="","",EDATE(I36,3)) -> 45440
A37: CUST0036 | B37: CHATURBHAI M PATEL | C37: 9558901139 | D37: GJ27BC0611 | E37: ACTIVA | F37: ACTIVA 3G | G37: D-403,KALPTARU HOME | H37: 44748 | I37: 44719 | J37: =IF(I37="","",EDATE(I37,3)) -> 44811
A38: CUST0037 | B38: JAY M KACNALIYA | C38: 9574883489 | D38: GJ27AL8884 | E38: DREEM YUGA | F38: HONDA | G38: B-606,MANSHROVER HI | H38: 43567 | I38: 43803 | J38: =IF(I38="","",EDATE(I38,3)) -> 43894
A39: CUST0038 | B39: BHAVESHBHAI LIMBACHIYA | C39: 9727605815 | D39: GJ02CH3185 | E39: AVENGER 150 | F39: AVENGER 150 STREET | G39: - | H39: - - | I39: 46012 | J39: =IF(I39="","",EDATE(I39,3)) -> 46102
A40: CUST0039 | B40: LALABHAI | C40: 9924081331 | D40: GJ27BF7027 | E40: BAJAJ V-150 | F40: V-150 | G40: B-174 UMIYA NAGAR,ARBUDA NAGAR | H40: 44298 | I40: 44534 | J40: =IF(I40="","",EDATE(I40,3)) -> 44624
A41: CUST0040 | B41: GHANASHYAMBHAI PATEL | C41: 9870099372 | D41: GJ27CL0716 | E41: BLACK | F41: TVSAPACHE160 | G41: 68,SHIVSANTI SOC | H41: 45353 | I41: 45325 | J41: =IF(I41="","",EDATE(I41,3)) -> 45415
A42: CUST0041 | B42: KALPESHBHAI PATEL | C42: 9586000888 | D42: GJ27AF2058 | E42: ACTIVA BLACK | F42: ACTIVA | G42: C,304 SUREYAM GRES | H42: 30/10/2020 | I42: 44134 | J42: =IF(I42="","",EDATE(I42,3)) -> 44226
A43: CUST0042 | B43: YES PATEL | C43: 8141648088 | D43: GJ01NE3563 | E43: ACTIVA BLACK | F43: ACTIVA | G43: R,31 VASUDEV BANGOLS | H43: 31/03/2021 | I43: 44286 | J43: =IF(I43="","",EDATE(I43,3)) -> 44377
A44: CUST0043 | B44: PATEL | C44: 1234567891 | D44: GJ01AB1245 | E44: SPLENDOR PLUS | F44: SPLENDOR PLUS | G44: VASTRAL | H44: 43597 | I44: 43804 | J44: =IF(I44="","",EDATE(I44,3)) -> 43895
A45: CUST0044 | B45: SATISH BHAI CHODHARI | C45: 9998105677 | D45: GJ27BR5443 | E45: ACTIVA | F45: ACTIVA 3G | G45: B.206 SONAHI SONA | H45: 14/02/2023 | I45: 44971 | J45: =IF(I45="","",EDATE(I45,3)) -> 45060
A46: CUST0045 | B46: RAJNIKANT BHAI PATEL | C46: 9427038847 | D46: GJ02BA3892 | E46: HF DELUX BLACK | F46: HF DELUXE | G46: C401,SARENAM RESIDANCY | H46: 44116 | I46: 44175 | J46: =IF(I46="","",EDATE(I46,3)) -> 44265
A47: CUST0046 | B47: VINAY BHAI GUPTA | C47: 9426445220 | D47: GJ27AG3242 | E47: MESTERO BLACK | F47: MESTRO | G47: C401,SAROVER 4 | H47: 16/10/2025 | I47: 45946 | J47: =IF(I47="","",EDATE(I47,3)) -> 46038
A48: CUST0047 | B48: PRAHLADBHAI PATEL | C48: 9925275874 | D48: GJ27AM3309 | E48: ACTIVA WHITE | F48: ACTIVA | G48: 86,MAGALM SOC, | H48: 43750 | I48: 43809 | J48: =IF(I48="","",EDATE(I48,3)) -> 43900
A49: CUST0048 | B49: CHIRAGBHAI | C49: 8140126461 | D49: GJ27BQ0352 | E49: HORENT160BACK | F49: HORENT | G49: O-201 ABJIBAPA | H49: 43750 | I49: 43809 | J49: =IF(I49="","",EDATE(I49,3)) -> 43900
A50: CUST0049 | B50: MANISHBHAI JETHANI | C50: 9033271081 | D50: GJ27S8038 | E50: PULSAR 150 | F50: PULSAR 150 | G50: A-502 GANESH HOME | H50: 45179 | I50: 45208 | J50: =IF(I50="","",EDATE(I50,3)) -> 45300
A51: CUST0050 | B51: KALPESH BHAI PATEL | C51: 9913765669 | D51: GJ27AJ8274 | E51: HONDASHINEBLACK | F51: HONDASHINE | G51: A1,307 SASHVAT 3 | H51: 44053 | I51: 44112 | J51: =IF(I51="","",EDATE(I51,3)) -> 44204
A52: CUST0051 | B52: NARAYNBHAI | C52: 9824039519 | D52: GJ01SH8916 | E52: ACTIVA | F52: ACTIVA 3G | G52: A-501 AVADH AEVNU | H52: - - | I52: - - | J52: =IF(I52="","",EDATE(I52,3)) -> #VALUE!
A53: CUST0052 | B53: SUNILBHAI RATILALPRAJAPATI | C53: 8160026627 | D53: GJ18DB8545 | E53: ACTIVA5GWHITE | F53: ACTIVA 5G | G53: A-401 RUDRA RE, | H53: 45358 | I53: 45476 | J53: =IF(I53="","",EDATE(I53,3)) -> 45568
A54: CUST0053 | B54: ARVINDBHAI PATEL | C54: 9879010349 | D54: GJ27AK3725 | E54: ACTIVA3GWHITE | F54: ACTIVA 3G | G54: A-101 SHRI NATH HIL, | H54: 30/10/2021 | I54: 44499 | J54: =IF(I54="","",EDATE(I54,3)) -> 44591
A55: CUST0054 | B55: JITENDHBHAI DABHI | C55: 9998330074 | D55: GJ01EH4523 | E55: SPLENDOR PLUS | F55: SPLENDOR PLUS | G55: RATANPURA | H55: - - | I55: 46012 | J55: =IF(I55="","",EDATE(I55,3)) -> 46102
A56: CUST0055 | B56: ASHISH BHAI SONI | C56: 9724302041 | D56: GJ27J2078 | E56: HF DELUX BLACK | F56: HF DELUXE | G56: B780,5553 GUJARAT HAU | H56: 45485 | I56: 45633 | J56: =IF(I56="","",EDATE(I56,3)) -> 45723
A57: CUST0056 | B57: SHIVESH TIVADI | C57: 9374023770 | D57: GJ27BJ4848 | E57: PLATINABACKES | F57: BAJAJ PLATINA ES | G57: D-302 KALPTRU HOME | H57: 31/01/2021 | I57: 44227 | J57: =IF(I57="","",EDATE(I57,3)) -> 44316
A58: CUST0057 | B58: ANUJ PARJAPATI | C58: 9712321267 | D58: GJ27BG5330 | E58: ISMART100CCHEROBLACK | F58: I SMART 100 CC | G58: 58 KARNAVTI BG | H58: 43781 | I58: 43810 | J58: =IF(I58="","",EDATE(I58,3)) -> 43901
A59: CUST0058 | B59: AKASH BHAI SAPRA | C59: 8128886004 | D59: GJ27BA0252 | E59: HEROXTREMBACK | F59: XTREME | G59: 78,RAJRATNA RAJENDERA PAREK | H59: 21/08/2025 | I59: 45890 | J59: =IF(I59="","",EDATE(I59,3)) -> 45982
A60: CUST0059 | B60: JAYESH BHAI RAMESH BHAI PATEL | C60: 7878343538 | D60: GJ02CM8129 | E60: JUPITER BKACK | F60: JUPITER | G60: B51,SURBHI SOC | H60: 45659 | I60: 45689 | J60: =IF(I60="","",EDATE(I60,3)) -> 45778
A61: CUST0060 | B61: PRAVINBHAI PRAJAPATI | C61: 9998901764 | D61: GJ01MC3351 | E61: PASSION PRO | F61: PASSION PRO | G61: 12 TEJENDRA TERNAMENT | H61: 18/08/2025 | I61: 45887 | J61: =IF(I61="","",EDATE(I61,3)) -> 45979
A62: CUST0061 | B62: RAMESHBHAI RAMOLIYA | C62: 9979884186 | D62: GJ27AB7257 | E62: SPLENDOR PLUS | F62: SPLENDOR PLUS | G62: A401 AVADH REDIDENCY | H62: 13/10/2022 | I62: 44847 | J62: =IF(I62="","",EDATE(I62,3)) -> 44939
A63: CUST0062 | B63: SAGAR PANCHAL | C63: 9727573791 | D63: GJ27AF3028 | E63: SPLENDERPROBLACK | F63: SPLENDOR PRO | G63: 306 MAHADEV RESIDENCY | H63: 23/10/2023 | I63: 45222 | J63: =IF(I63="","",EDATE(I63,3)) -> 45314
A64: CUST0063 | B64: BHAVIK BHAI PATEL | C64: 9724170393 | D64: GJ27R0446 | E64: ACTIVA WHITE | F64: ACTIVA | G64: B31 TRIFEV SOCIETY | H64: - - | I64: 46012 | J64: =IF(I64="","",EDATE(I64,3)) -> 46102
A65: CUST0064 | B65: RAHULBHAI | C65: 7383954248 | D65: GJ27Q2390 | E65: DREEM YUGA | F65: HONDA | G65: 101 M,ANAGATIRTH SOCIETY | H65: 14/06/2020 | I65: 43996 | J65: =IF(I65="","",EDATE(I65,3)) -> 44088
A66: CUST0065 | B66: RAJUBHAI | C66: 9978092409 | D66: GJ02BA0477 | E66: HONDASHINEBLACK | F66: HONDASHINE | G66: B201 VED SHREE RESIDENCY | H66: 16/12/2019 | I66: 43815 | J66: =IF(I66="","",EDATE(I66,3)) -> 43906
A67: CUST0066 | B67: PUROHIT PRAVINBHAI | C67: 9409624414 | D67: GJ27BC5222 | E67: PLEASURE BLACK | F67: PLEASURE | G67: G 101 SHREE SHAYANG | H67: 18/11/2024 | I67: 45614 | J67: =IF(I67="","",EDATE(I67,3)) -> 45706
A68: CUST0067 | B68: VIKRAM SINH DARBAR | C68: 9904483481 | D68: GJ01LP0529 | E68: ACTIVA WHITE | F68: ACTIVA | G68: PUSHP 2, I-206 | H68: 15/12/2019 | I68: 43814 | J68: =IF(I68="","",EDATE(I68,3)) -> 43905
A69: CUST0068 | B69: DHASHARATHBHAI | C69: 9825961805 | D69: GJ01LE9171 | E69: ACTIVA WHITE | F69: ACTIVA | G69: 21 YOGESHWAR PARK | H69: 15/02/2021 | I69: 44242 | J69: =IF(I69="","",EDATE(I69,3)) -> 44331
A70: CUST0069 | B70: PARESHBHAI PANCHAL | C70: 9824040763 | D70: GJ27BG5111 | E70: ACTIVA BLACK | F70: ACTIVA | G70: AVADHA RESIDENCY | H70: 45719 | I70: 45719 | J70: =IF(I70="","",EDATE(I70,3)) -> 45811
A71: CUST0070 | B71: GUPTA VISHNUBHAI | C71: 9898919382 | D71: GJ27CD8610 | E71: ACTIVA BLACK | F71: ACTIVA | G71: 53 KRISHNA DARSHAN SOC | H71: 20/04/2025 | I71: 45767 | J71: =IF(I71="","",EDATE(I71,3)) -> 45858
A72: CUST0071 | B72: HITESHBHAI TANK | C72: 7878233751 | D72: GJ27BF0634 | E72: SPLENDERPROBLACK | F72: SPLENDOR PRO | G72: 32 KARTIK SOC | H72: 13/08/2024 | I72: 45517 | J72: =IF(I72="","",EDATE(I72,3)) -> 45609
A73: CUST0072 | B73: PRAJAPATI JIGNESHKUMAR | C73: 9724353745 | D73: GJ27AN0605 | E73: SPLENDOR PLUS | F73: SPLENDOR PLUS | G73: A54 ALOK 5 | H73: 45056 | I73: 45204 | J73: =IF(I73="","",EDATE(I73,3)) -> 45296
A74: CUST0073 | B74: RAJUBHAI PATEL | C74: 9601313345 | D74: GJ27CH8832 | E74: ACTIVA BLACK | F74: ACTIVA | G74: C 501 NAIYA 1 | H74: 28/10/2020 | I74: 44132 | J74: =IF(I74="","",EDATE(I74,3)) -> 44224
A75: CUST0074 | B75: PATEL RAMANLAL | C75: 9510802142 | D75: GJ27AK0075 | E75: ACTIVA BLACK | F75: ACTIVA | G75: B 207 RUDRA RESIDENCY | H75: 45601 | I75: 45423 | J75: =IF(I75="","",EDATE(I75,3)) -> 45515
A76: CUST0075 | B76: CHAUHAN RATANSINH | C76: 7779092900 | D76: GJ02CQ9014 | E76: HORENT160BACK | F76: HORENT | G76: A502 RUDRA RESIDENCY | H76: 19/11/2025 | I76: 45980 | J76: =IF(I76="","",EDATE(I76,3)) -> 46072
A77: CUST0076 | B77: KAMLESHBHAI TETVA | C77: 9727827432 | D77: GJ27AR5608 | E77: HF DELUX BLACK | F77: HF DELUXE | G77: 31 VRUNDAVAN DHAM | H77: 19/12/2019 | I77: 43818 | J77: =IF(I77="","",EDATE(I77,3)) -> 43909
A78: CUST0077 | B78: RAJPUT CHTNABEN | C78: 8160205540 | D78: GJ01SD2040 | E78: ACTIVA BLACK | F78: ACTIVA | G78: 60 SHIVANAND BUNGLOWS | H78: 19/12/2019 | I78: 43818 | J78: =IF(I78="","",EDATE(I78,3)) -> 43909
A79: CUST0078 | B79: PANCHAL DHAVALBHAI | C79: 9898273515 | D79: GJ27BM2841 | E79: SPLENDOR PLUS | F79: SPLENDOR PLUS | G79: SHOP 3 SATVA 2 | H79: 46267 | I79: 46062 | J79: =IF(I79="","",EDATE(I79,3)) -> 46151
A80: CUST0079 | B80: JAGURTI HITESHBHAI SOLANKI | C80: 7359406545 | D80: GJ24C5773 | E80: SPLENDOR PLUS | F80: SPLENDOR PLUS | G80: D 108 NAIYA APP | H80: 21/06/2023 | I80: 45098 | J80: =IF(I80="","",EDATE(I80,3)) -> 45190
A81: CUST0080 | B81: VIMALBHAI PANCHAL | C81: 9879810835 | D81: GJ27CA2447 | E81: SPLENDOR PLUS | F81: SPLENDOR PLUS | G81: DABHIVAS | H81: 30/10/2020 | I81: 44134 | J81: =IF(I81="","",EDATE(I81,3)) -> 44226
A82: CUST0081 | B82: JAY M KACHALIYA | C82: 9574883489 | D82: GJ27CJ5491 | E82: SHINE | F82: CB SHINE | G82: B606 MANSAROVAR HIGHTES | H82: 13/06/2024 | I82: 45456 | J82: =IF(I82="","",EDATE(I82,3)) -> 45548
A83: CUST0082 | B83: JADAV SAHIL | C83: 8401999035 | D83: GJ27CA7357 | E83: ACTIVA BLACK | F83: ACTIVA | G83: PUSHP 2 | H83: 45963 | I83: 45699 | J83: =IF(I83="","",EDATE(I83,3)) -> 45788
A84: CUST0083 | B84: DIPEN KUMAR | C84: 9724099068 | D84: GJ27AM8794 | E84: DREEM YUGA | F84: HONDA | G84: B703 SURYAM PRIDE | H84: 29/09/2024 | I84: 45564 | J84: =IF(I84="","",EDATE(I84,3)) -> 45655
A85: CUST0084 | B85: SURESHBHAI | C85: 7405791202 | D85: GJ27AG0331 | E85: PASSION PRO | F85: PASSION PRO | G85: KALPTARU RESIDENCY | H85: - - | I85: 46012 | J85: =IF(I85="","",EDATE(I85,3)) -> 46102
A86: CUST0085 | B86: AJAY PATEL | C86: 9979228423 | D86: GJ27AC8300 | E86: MESTERO BLACK | F86: MESTRO | G86: A204 SHANTIKETAN3 | H86: - - | I86: 46012 | J86: =IF(I86="","",EDATE(I86,3)) -> 46102
A87: CUST0086 | B87: MUKESH CHAUDHARY | C87: 9924787506 | D87: GJ27BM1139 | E87: ACTIVA BLACK | F87: ACTIVA | G87: 24 TULSI BUNGLOW | H87: 29/10/2024 | I87: 45594 | J87: =IF(I87="","",EDATE(I87,3)) -> 45686
A88: CUST0087 | B88: BHAVESHBHAI TRIVEDI | C88: 9426331202 | D88: GJ07AP1764 | E88: GLAMOUR BLACK | F88: GLAMOUR | G88: 30 SHIVANAND BUNGLOW | H88: - - | I88: 46012 | J88: =IF(I88="","",EDATE(I88,3)) -> 46102
A89: CUST0088 | B89: PRAKASHBHAI | C89: 9925100147 | D89: GJ27CH4070 | E89: HONDA LIVO | F89: HONDA LIVO | G89: A503 SANSKRUTI RESIDENCY | H89: 29/02/2020 | I89: 43890 | J89: =IF(I89="","",EDATE(I89,3)) -> 43980
A90: CUST0089 | B90: PRANAVBHAI | C90: 9925938887 | D90: GK27AF3509 | E90: MAHINDRA REDIO BLACK | F90: REDIO | G90: A1 101 AKSHARDHAM RESIDENCY | H90: - - | I90: - - | J90: =IF(I90="","",EDATE(I90,3)) -> #VALUE!
A91: CUST0090 | B91: PATEL MAYANK | C91: 9904088974 | D91: GJ27CE9867 | E91: PULSAR 150 | F91: PULSAR 150 | G91: 4 JAY SASWAT NAGAR | H91: 30/01/2025 | I91: 45687 | J91: =IF(I91="","",EDATE(I91,3)) -> 45777
A92: CUST0091 | B92: RUCHITA BEN MISTRI | C92: 7984671128 | D92: GJ01ML6291 | E92: TVS WEGO WHITE | F92: WEGO | G92: D606 VEDRAJ | H92: 44024 | I92: 44172 | J92: =IF(I92="","",EDATE(I92,3)) -> 44262
A93: CUST0092 | B93: DR PIYUSHBHAI | C93: 8200697278 | D93: GJ01MA4265 | E93: PASSION PRO | F93: PASSION PRO | G93: 6 DIVYAKUNJ | H93: 23/07/2025 | I93: 45861 | J93: =IF(I93="","",EDATE(I93,3)) -> 45953
A94: CUST0093 | B94: PATEL APURVA | C94: 8866502653 | D94: GJ27CE4075 | E94: BLACK | F94: TVSAPACHE160 | G94: 47 MADHAV PARK 2 | H94: 20/05/2025 | I94: 45797 | J94: =IF(I94="","",EDATE(I94,3)) -> 45889
A95: CUST0094 | B95: PRITESH BHAI | C95: 9879604374 | D95: GJ01EP5659 | E95: PASSIN PLUS | F95: PASSIN PLUS | G95: 65 BANSHI SOC | H95: - - | I95: - - | J95: =IF(I95="","",EDATE(I95,3)) -> #VALUE!
A96: CUST0095 | B96: PRAKASH BHAI | C96: 8849454921 | D96: GJ01SY1981 | E96: ACTIVA BLACK | F96: ACTIVA | G96: VASTRAL | H96: 22/03/2021 | I96: 44277 | J96: =IF(I96="","",EDATE(I96,3)) -> 44369
A97: CUST0096 | B97: BHAVINBHAI ASHWINBHAI PATEL | C97: 9909573119 | D97: GJ27BM7779 | E97: BLACK | F97: TVSAPACHE160 | G97: NADIYAD | H97: 21/01/2020 | I97: 43851 | J97: =IF(I97="","",EDATE(I97,3)) -> 43942
A98: CUST0097 | B98: PRAKASH THAKOR | C98: 9824540194 | D98: GJ27J7999 | E98: ACTIVA BLACK | F98: ACTIVA | G98: B101 OMKAR RESIDENCY | H98: - - | I98: - - | J98: =IF(I98="","",EDATE(I98,3)) -> #VALUE!
A99: CUST0098 | B99: PRADIPBHAI | C99: 9898006971 | D99: GJ27N3609 | E99: DISCOVER 100 CC | F99: DISCOVER 100 | G99: 26 SHIVANAND BUNGLOW | H99: 45906 | I99: 45817 | J99: =IF(I99="","",EDATE(I99,3)) -> 45909
A100: CUST0099 | B100: RONAKBHAI PATEL | C100: 8980584713 | D100: GJ09CK8286 | E100: CBZ XTREM HERO | F100: XTREME | G100: 502 ASOPALAV SOC | H100: 28/02/2026 | I100: 46081 | J100: =IF(I100="","",EDATE(I100,3)) -> 46170
...

Sheet customer
A1: Name | B1: phone | C1: Vehicle | D1: plate_number
A2: HARSHADBHAI VAGHELA | B2: 9898284327 | C2: HEROPESSIONPROBLACK | D2: GJ27CN9504
A3: JASHWANT PRAJAPATI | B3: 9824820017 | C3: HONDASHINEBLACK | D3: GJ27BJ9478
A4: NARESHBHAI PATEL | B4: 9924748010 | C4: ACTIVA BLACK | D4: GJ27E4534
A5: YOGESH MAHESHBHAI GAJJAR | B5: 9601065325 | C5: ACTIVA BLACK | D5: GJ27Q1004
A6: UPENDRABHAI PATEL | B6: 9974591740 | C6: MAHINDRACENTURIOBLAC | D6: GJ01SB0672
A7: DHAVALBHAI | B7: 9726937785 | C7: HEROPESSIONPROBLACK | D7: GJ27BR2787
A8: PRAKASHBHAI THAKOR | B8: 9824540194 | C8: DREEM YUGA | D8: GJ27J7699
A9: KIRAN BHAI PATEL | B9: 9924691071 | C9: DREEM YUGA | D9: GJ02BL5262
A10: ANKIT PATEL | B10: 9737548662 | C10: ACTIVA BLACK | D10: GJ01JN6237
A11: DHARMIK BHARATBHAI PATEL | B11: 7777981411 | C11: ACTIVABLACK | D11: GJ27BK9776
A12: KEVALBHAI KIRITBHAI PATEL | B12: 9979124383 | C12: ACTIVA | D12: GJ27BG3046
A13: NIKUBHAI PATEL | B13: 9099036478 | C13: ACTIVA | D13: GJ7BG5464
... A428: PRIYANK R KARPITYA | B428: 9737631780 | C428: PASSION XPRO | D428: GJ27CL3832
A429: RAHULBHAI NARESHBHAI SAMKUNIYA | C429: ACCESS125 OLD | D429: GJ01SD2657
A430: DESAI HARGOVANDBHAI BAMJI | B430: 9998786665 | C430: ES | D430: GJ24AC0237
A431: NAGINBHAI SOLANKI | B431: 9714386220 | C431: PASSION PRO | D431: GJ07CQ7214
A432: HIRALALA GOKULRAM CHAUDRI | B432: 9825778422 | C432: ACTIVA BLACK | D432: GJ27P9484
A433: YOGESHBHAI DINESHBHAI SHARMA | B433: 9925045283 | C433: HONDASHINEBLACK | D433: GJ01FU2966
A434: JITENDRABHAI P TRIVEDI | B434: 9376947022 | C434: TVS WEGO WHITE | D434: GJ05GL5355
A435: JITENDRABHAI P TRIVEDI. | B435: 9376947022 | C435: PASSION PRO | D435: GJ05FC1188
A436: SHILPABEN HARSHADBHAI PANCHAL | B436: 9426037332 | C436: JUPITER BKACK | D436: GJ27CJ6478
A437: PRAVINBHAI D CHAUHAN | B437: 9925505689 | C437: SHINE | D437: GJ27CK0651
A438: JITESHBHAI PRATABBHAI ZALA | B438: 6352764698 | C438: SPLENDOR PLUS | D438: GJ27CA9250
A439: HARGOVAND K DESAI | B439: 9998786665 | C439: ACTIVA BLACK | D439: GJ01JQ1218
A440: NITINBHAI J PATEL | B440: 9924407746 | C440: ACTIVA BLACK | D440: GJ27BK6184
A441: ASHVINBHAI GANGARAMBHAI PATEL | B441: 9825014281 | C441: MESTERO BLACK | D441: GJ27AG560
... A580: VANITABEN PATEL | B580: 9998994713 | C580: JUPITER BKACK | D580: GJ27AQ0674
A581: MIT H PATEL | C581: PASSION PRO | D581: GJ27A51798
A582: BHARATBHAI R PARMAR | B582: 7874911351 | C582: ACTIVA BLACK | D582: GJ01SB4703
A583: NIRAJBHAI YADAV | B583: 9722821056 | C583: PASSION PRO | D583: GJ27F5685
A584: HARDIKBHAI B PATEL | B584: 7016952030 | C584: SPLENDOR PLUS | D584: GJ27AN9937
A585: JAYMINBHAI J PATEL | B585: 7600914791 | C585: SPLENDOR PLUS | D585: GJ01FR0881
A586: MEHULBHAI S JAIN | B586: 9726442111 | C586: ACTIVABLACK | D586: GJ27C7048
A587: JAYKUMAR PATEL | B587: 7878343538 | C587: DREEM YUGA | D587: GJ27S1405
A588: HARDEVSINH VAGHELA | B588: 9724766607 | C588: PASSION PRO | D588: GJ27BP5071
A589: DILIPBHAI PATEL | B589: 9426753128 | C589: SPLENDOR PLUS | D589: GJ24IT4597
A590: DHARMESHBHAI PATEL | B590: 9979534182 | C590: BLACK | D590: GJ27BH9670
A591: BHAVESHBHAI M PATEL | B591: 9537667785 | C591: HF DELUX BLACK | D591: GJ01SH5221
A592: DHRUVBHAI B PATEL | B592: 8155856422 | C592: ACTIVA BLACK | D592: GJ27AD2402
A593: JATINBHAI C PATEL | B593: 9662170035 | C593: HONDASHINEBLACK | D593: GJ24J3372
... A994: KISHNKANTBHAI | B994: 9510885551 | C994: SPLENDOR PLUS | D994: GJ01FK2022
A995: BHAVESHBHAI PITRODA | C995: ACTIVA3GWHITE | D995: GJ27AF8415
A996: PARTH PATEL | B996: 9979539443 | C996: PASSION PRO | D996: GJ27AF9660
A997: JAYESH MANUBHAI PATEL | B997: 9574479558 | C997: SPLENDOR PLUS | D997: GJ27L9558
A998: PARMODBHAI | B998: 9096295640 | C998: PASSION XPRO | D998: GJ27BD6329
A999: MAHENRBHAI P PATEL | B999: 9429132183 | C999: ACCESS125 OLD | D999: GJ01NE0186
A1000: UPENDRBHAI VASHUDEVBHAI PATEL | B1000: 9974591740 | C1000: DISCOVER 100 CC | D1000: GJ01NA7902
A1001: DIPIKABEN R PARMAR | B1001: 7096806621 | C1001: ACTIVABLACK | D1001: 1234567891
A1002: ISHAVARBHAI DESAI | B1002: 7698667655 | C1002: AVENGER 150 | D1002: GJ27BB2021
A1003: JAY | B1003: 9510160823 | C1003: ACTIVA | D1003: GJ27CD9291
A1004: JAGADISHBHAI PATEL | B1004: 9574635501 | C1004: SPLENDOR PLUS | D1004: GJ27BA5747
A1005: BHIKHABHAI PANCHAL | B1005: 9725785160 | C1005: HONDAGRAZLA | D1005: GJ27CN8636
A1006: ANILBHAI DAVE | B1006: 7383268947 | C1006: JUPITER BKACK | D1006: GJ27BP6321
A1007: PIRYAKBHAI B PATEL | B1007: 8141525371 | C1007: ACTIVA | D1007: GJ27BJ4291
A1008: VISHAL KATHARELA | B1008: 9722140140 | C1008: GLAMOUR BLACK | D1008: GJ27AS8296
A1009: UMANG GUPATA | B1009: 9898012992 | C1009: SPLENDOR PLUS | D1009: GJ27AS4835
A1010: RAJESHBHAI SOLANKI | B1010: 8454936060 | C1010: GLAMOUR BLACK | D1010: GJ27CG8716
A1011: KISHAN R PATEL | B1011: 9537755093 | C1011: ACTIVA | D1011: GJ02BF4269
A1012: URVISH PRAJAPATI | B1012: 8460832369 | C1012: SPLENDOR PLUS | D1012: GJ01MG7263
A1013: AKASHBHAI RAJUBHAI PATEL | B1013: 9727960345 | C1013: JUPITER BKACK | D1013: GJ08AR4661
... A1214: DINESHBHAI PARSHOTMBHAI PATEL | B1214: 9825678903 | C1214: JUPITER BKACK | D1214: GJ27AK1082
A1215: POOJABEN MACHI C/O AMITBHAI | C1215: ACTIVABLACK | D1215: GJ27J9423
A1216: VISHALBAI RAMESHBHAI PATEL | B1216: 9327989996 | C1216: ACTIVA | D1216: GJ27AM8404
A1217: VISHANUBHAI RAMAJIBHAI DESAI | B1217: 9825848500 | C1217: SPLENDOR PLUS | D1217: GJ18CE9921
A1218: MAULIKBHAI VASANI | B1218: 9428705983 | C1218: DISCOVER 100 CC | D1218: GJ11EE9461
A1219: CHUNILAL P PATEL | B1219: 9429208017 | C1219: ACTIVA | D1219: GJ27AM8051
A1220: DILIPBHAI MULJIBHAI PATEL | B1220: 8200674817 | C1220: ACCESS125 OLD | D1220: GJ01SX9602
A1221: AVINASHBHAI JAYNTIBHAI PATEL | B1221: 9978338704 | C1221: PLEASURE BLACK | D1221: GJ09AP4951
A1222: SURAJITSHINGH CHAUHAN | B1222: 9824614055 | C1222: ACTIVA125BLACK | D1222: GJ27BG6703
A1223: SACHINBHAI BIPINBHAI PATEL | B1223: 7600575109 | C1223: SPLENDOR PLUS | D1223: GJ27AC5686
A1224: DEVRAJBHAI PATEL | B1224: 9998365109 | C1224: DISCOVER 125 | D1224: GJ01PQ205
A1225: VINAYBHAI RAMEE | B1225: 8000391901 | C1225: ACTIVABLACK | D1225: GJ01LP4761
A1226: VIRALBHAI PATEL | B1226: 8980019330 | C1226: DISCOVER 125 | D1226: GJ27Q5559
A1227: HEMANTBHAI KIRITBHAI PATEL | B1227: 8140479136 | C1227: PASSIN PLUS | D1227: GJ07AS5185
... A1286: DIPKUMAR JAYESHBHAI PATEL | B1286: 7383663368 | C1286: DISCOVER 100 CC | D1286: GJ02BB4108
A1287: MANISHBHAI (AMUL MILK) | C1287: ACTIVABLACK | D1287: GJ27CL6898
A1288: JAGDISHBHAI PARBHUBHAI PATEL | B1288: 8141491947 | C1288: HONDASHINEBLACK | D1288: GJ01LJ5129
A1289: DHARMESH PATEL | B1289: 7698286286 | C1289: PULSAR 150 | D1289: GJ08BG0286
A1290: BHARATBHAI B PATEL | B1290: 9427031331 | C1290: ACTIVA125BLACK | D1290: GJ27BK7183
A1291: DEVENDRAKUMAR CHIMANBHAI PATEL | B1291: 8780159765 | C1291: YAMAHA SZRR | D1291: GJ09CD3809
A1292: MANOJBHAI SAWMI | B1292: 9649948127 | C1292: ACTIVA125BLACK | D1292: GJ27CN5111
A1293: DARSHAN S PATEL | B1293: 8488944661 | C1293: CD DELUXE HERO | D1293: GJ27L8752
A1294: UMESHBHAI SHREERAM | B1294: 8460402681 | C1294: SUZUKIGIXXER | D1294: GJ27AM3644
A1295: SACHINBHAI VINODBHAI PATEL | B1295: 9913201025 | C1295: SPLENDOR PLUS | D1295: GJ02CS3887
A1296: BRIJESHSINGH RAJPUT | B1296: 9228346029 | C1296: DREEM YUGA | D1296: GJ27AS7875
A1297: MAYUR B PATEL | B1297: 9974452875 | C1297: DISCOVER135BLACK | D1297: GJ01JD9084
A1298: BHAVIKBHAI KIRITBHAI PATEL | B1298: 8141613540 | C1298: SPLENDERPROBLACK | D1298: GJ27J9405
A1299: RUTULBHAI PRAJAPATI | B1299: 9925825801 | C1299: SPLENDOR PLUS | D1299: GJ27BQ5746
... A1591: GURURAJ BELAWADI | B1591: 7587040374 | C1591: ACTIVA125BLACK | D1591: KA25HA1252
A1592: RAMESHBHAI PRAJAPTI | C1592: ACTIVA | D1592: GJ08AD3790
A1593: UPENDRABHAI NATAVARBHAI PATEL | B1593: 9824637678 | C1593: TVS WEGO WHITE | D1593: GJ01MC7261
A1594: DHURV PATEL | B1594: 9714381138 | C1594: ACTIVA5GWHITE | D1594: GJ27CZ4189
A1595: KEVAL DHARMENDRABHAI PATEL | B1595: 9925580731 | C1595: PASSION XPRO | D1595: GJ07CE0779
A1596: NAITIKBHAI RAJESHBHAI PATEL C/O DHURV | B1596: 8866568730 | C1596: ACTIVA | D1596: GJ27AS8640
A1597: JETALBHAI CHAUDHARI | B1597: 9925163095 | C1597: SPLENDOR PLUS | D1597: GJ09CP1427
A1598: KIRITBHAI PRATAPBHAI DABHI | B1598: 9724060700 | C1598: SPLENDERPROBLACK | D1598: GJ27A7586
A1599: PARVINBHAI SATARAMBHAI PARAJAPATI | B1599: 9924769506 | C1599: ACTIVABLACK | D1599: GJ27CH4789
A1600: PARESHBHAI LAXSHAMANBHAI PATEL | B1600: 7567200667 | C1600: DISCOVER 100 CC | D1600: GJ27E0373
A1601: RAKESHBHAI BHARATBHAI PATEL | B1601: 7698713472 | C1601: HONDASHINEBLACK | D1601: GJ01JV4498
...

Sheet Bookings
A1: Booking ID | B1: Customer ID | C1: C_Name | D1: C_phone | E1: Vehi_Num | F1: Booking Date | G1: Service Date | H1: Status
A2: =IF(B2="","", "BOOK"&TEXT(ROW()-1,"0000")) -> BOOK0001 | B2: CUST0001 | C2: =IFERROR(VLOOKUP(B2,Customers!A:D,2,FALSE),"") -> HARSHADBHAI VAGHELA | D2: =IFERROR(VLOOKUP(B2,Customers!A:D,3,FALSE),"") -> 9898284327 | E2: =IFERROR(VLOOKUP(B2,Customers!A:D,4,FALSE),"") -> GJ27CN9504 | F2: =IF(B2="","",TODAY()) -> 46182 | H2: Completed
A3: =IF(B3="","", "BOOK"&TEXT(ROW()-1,"0000")) -> BOOK0002 | B3: CUST0010 | C3: =IFERROR(VLOOKUP(B3,Customers!A:D,2,FALSE),"") -> DHARMIK BHARATBHAI PATEL | D3: =IFERROR(VLOOKUP(B3,Customers!A:D,3,FALSE),"") -> 7777981411 | E3: =IFERROR(VLOOKUP(B3,Customers!A:D,4,FALSE),"") -> GJ27BK9776 | F3: =IF(B3="","",TODAY()) -> 46182
A4: =IF(B4="","", "BOOK"&TEXT(ROW()-1,"0000")) -> BOOK0003 | B4: CUST0529 | C4: =IFERROR(VLOOKUP(B4,Customers!A:D,2,FALSE),"") -> ROHITBHAI R PATEL | D4: =IFERROR(VLOOKUP(B4,Customers!A:D,3,FALSE),"") -> 6355973218 | E4: =IFERROR(VLOOKUP(B4,Customers!A:D,4,FALSE),"") -> GJ08BJ8846 | F4: =IF(B4="","",TODAY()) -> 46182
A5: =IF(B5="","", "BOOK"&TEXT(ROW()-1,"0000")) | C5: =IFERROR(VLOOKUP(B5,Customers!A:D,2,FALSE),"") | D5: =IFERROR(VLOOKUP(B5,Customers!A:D,3,FALSE),"") | E5: =IFERROR(VLOOKUP(B5,Customers!A:D,4,FALSE),"") | F5: =IF(B5="","",TODAY())
A6: =IF(B6="","", "BOOK"&TEXT(ROW()-1,"0000")) | C6: =IFERROR(VLOOKUP(B6,Customers!A:D,2,FALSE),"") | D6: =IFERROR(VLOOKUP(B6,Customers!A:D,3,FALSE),"") | E6: =IFERROR(VLOOKUP(B6,Customers!A:D,4,FALSE),"") | F6: =IF(B6="","",TODAY())
A7: =IF(B7="","", "BOOK"&TEXT(ROW()-1,"0000")) | C7: =IFERROR(VLOOKUP(B7,Customers!A:D,2,FALSE),"") | D7: =IFERROR(VLOOKUP(B7,Customers!A:D,3,FALSE),"") | E7: =IFERROR(VLOOKUP(B7,Customers!A:D,4,FALSE),"") | F7: =IF(B7="","",TODAY())
A8: =IF(B8="","", "BOOK"&TEXT(ROW()-1,"0000")) | C8: =IFERROR(VLOOKUP(B8,Customers!A:D,2,FALSE),"") | D8: =IFERROR(VLOOKUP(B8,Customers!A:D,3,FALSE),"") | E8: =IFERROR(VLOOKUP(B8,Customers!A:D,4,FALSE),"") | F8: =IF(B8="","",TODAY())
A9: =IF(B9="","", "BOOK"&TEXT(ROW()-1,"0000")) | C9: =IFERROR(VLOOKUP(B9,Customers!A:D,2,FALSE),"") | D9: =IFERROR(VLOOKUP(B9,Customers!A:D,3,FALSE),"") | E9: =IFERROR(VLOOKUP(B9,Customers!A:D,4,FALSE),"") | F9: =IF(B9="","",TODAY())
A10: =IF(B10="","", "BOOK"&TEXT(ROW()-1,"0000")) | C10: =IFERROR(VLOOKUP(B10,Customers!A:D,2,FALSE),"") | D10: =IFERROR(VLOOKUP(B10,Customers!A:D,3,FALSE),"") | E10: =IFERROR(VLOOKUP(B10,Customers!A:D,4,FALSE),"") | F10: =IF(B10="","",TODAY())
A11: =IF(B11="","", "BOOK"&TEXT(ROW()-1,"0000")) | C11: =IFERROR(VLOOKUP(B11,Customers!A:D,2,FALSE),"") | D11: =IFERROR(VLOOKUP(B11,Customers!A:D,3,FALSE),"") | E11: =IFERROR(VLOOKUP(B11,Customers!A:D,4,FALSE),"") | F11: =IF(B11="","",TODAY())
A12: =IF(B12="","", "BOOK"&TEXT(ROW()-1,"0000")) | C12: =IFERROR(VLOOKUP(B12,Customers!A:D,2,FALSE),"") | D12: =IFERROR(VLOOKUP(B12,Customers!A:D,3,FALSE),"") | E12: =IFERROR(VLOOKUP(B12,Customers!A:D,4,FALSE),"") | F12: =IF(B12="","",TODAY())
A13: =IF(B13="","", "BOOK"&TEXT(ROW()-1,"0000")) | C13: =IFERROR(VLOOKUP(B13,Customers!A:D,2,FALSE),"") | D13: =IFERROR(VLOOKUP(B13,Customers!A:D,3,FALSE),"") | E13: =IFERROR(VLOOKUP(B13,Customers!A:D,4,FALSE),"") | F13: =IF(B13="","",TODAY())
A14: =IF(B14="","", "BOOK"&TEXT(ROW()-1,"0000")) | C14: =IFERROR(VLOOKUP(B14,Customers!A:D,2,FALSE),"") | D14: =IFERROR(VLOOKUP(B14,Customers!A:D,3,FALSE),"") | E14: =IFERROR(VLOOKUP(B14,Customers!A:D,4,FALSE),"") | F14: =IF(B14="","",TODAY())
A15: =IF(B15="","", "BOOK"&TEXT(ROW()-1,"0000")) | C15: =IFERROR(VLOOKUP(B15,Customers!A:D,2,FALSE),"") | D15: =IFERROR(VLOOKUP(B15,Customers!A:D,3,FALSE),"") | E15: =IFERROR(VLOOKUP(B15,Customers!A:D,4,FALSE),"") | F15: =IF(B15="","",TODAY())
A16: =IF(B16="","", "BOOK"&TEXT(ROW()-1,"0000")) | C16: =IFERROR(VLOOKUP(B16,Customers!A:D,2,FALSE),"") | D16: =IFERROR(VLOOKUP(B16,Customers!A:D,3,FALSE),"") | E16: =IFERROR(VLOOKUP(B16,Customers!A:D,4,FALSE),"") | F16: =IF(B16="","",TODAY())
... A248: =IF(B248="","", "BOOK"&TEXT(ROW()-1,"0000")) | C248: =IFERROR(VLOOKUP(B248,Customers!A:D,2,FALSE),"") | D248: =IFERROR(VLOOKUP(B248,Customers!A:D,3,FALSE),"") | E248: =IFERROR(VLOOKUP(B248,Customers!A:D,4,FALSE),"") | F248: =IF(B248="","",TODAY())
A249: =IF(B249="","", "BOOK"&TEXT(ROW()-1,"0000"))
A250: =IF(B250="","", "BOOK"&TEXT(ROW()-1,"0000"))
A251: =IF(B251="","", "BOOK"&TEXT(ROW()-1,"0000"))
A252: =IF(B252="","", "BOOK"&TEXT(ROW()-1,"0000"))
A253: =IF(B253="","", "BOOK"&TEXT(ROW()-1,"0000"))
A254: =IF(B254="","", "BOOK"&TEXT(ROW()-1,"0000"))
A255: =IF(B255="","", "BOOK"&TEXT(ROW()-1,"0000"))
A256: =IF(B256="","", "BOOK"&TEXT(ROW()-1,"0000"))
A257: =IF(B257="","", "BOOK"&TEXT(ROW()-1,"0000"))
A258: =IF(B258="","", "BOOK"&TEXT(ROW()-1,"0000"))
A259: =IF(B259="","", "BOOK"&TEXT(ROW()-1,"0000"))
A260: =IF(B260="","", "BOOK"&TEXT(ROW()-1,"0000"))
... A510: =IF(B510="","", "BOOK"&TEXT(ROW()-1,"0000"))
